[{"id":"27000","page":[],"created":"15-12-2000","published":false},{"id":27001,"page":[],"created":"01-01-1995","published":false},{"id":27002,"page":[],"created":"28-06-1996","published":false},{"id":27003,"page":[],"created":"04-02-1997","published":false},{"id":27004,"page":[],"created":"01-09-1996","published":false},{"id":27005,"page":[],"created":"01-07-1995","published":false},{"id":27006,"page":[],"created":"01-01-1995","published":false},{"id":27007,"page":[],"created":"29-07-1996","published":false},{"id":27008,"page":[],"created":"14-12-1998","published":false},{"id":27009,"page":[],"created":"01-01-1995","published":false},{"id":27010,"page":[],"created":"01-01-1995","published":false},{"id":27011,"page":[],"created":"17-07-1998","published":false},{"id":27012,"page":[],"created":"29-01-1997","published":false},{"id":27013,"page":[],"created":"02-04-1997","published":false},{"id":27014,"page":[],"created":"25-04-1997","published":false},{"id":27015,"page":[],"created":"17-05-2001","published":false},{"id":27016,"page":[],"created":"01-01-1995","published":false},{"id":27017,"page":[],"created":"24-06-1996","published":false},{"id":27018,"page":[],"created":"16-06-1996","published":false},{"id":27019,"page":[],"created":"15-05-1998","published":false},{"id":27020,"page":[],"created":"15-05-1996","published":false},{"id":27021,"page":[],"created":"08-06-1998","published":false},{"id":27022,"page":[],"created":"20-01-1997","published":false},{"id":27023,"page":[],"created":"01-01-1995","published":false},{"id":27024,"page":[],"created":"01-01-1995","published":false},{"id":27025,"page":[],"created":"04-05-1997","published":false},{"id":27026,"page":[],"created":"22-05-1996","published":false},{"id":27027,"page":[],"created":"08-03-2001","published":false},{"id":27028,"page":[],"created":"01-01-1995","published":false},{"id":27029,"page":[],"created":"28-02-2001","published":false},{"id":27030,"page":[],"created":"12-05-1998","published":false},{"id":27031,"page":[],"created":"01-01-1995","published":false},{"id":27032,"page":[],"created":"24-07-1996","published":false},{"id":27033,"page":[],"created":"24-05-1996","published":false},{"id":27034,"page":[],"created":"11-04-1997","published":false},{"id":27035,"page":[],"created":"01-01-1995","published":false},{"id":27036,"page":[],"created":"07-09-2000","published":false},{"id":27037,"page":[],"created":"29-05-1996","published":false},{"id":27038,"page":[],"created":"28-03-1996","published":false},{"id":27039,"page":[],"created":"17-06-1996","published":false},{"id":27040,"page":[],"created":"03-08-1995","published":false},{"id":27041,"page":[],"created":"13-05-1996","published":false},{"id":27042,"page":[],"created":"08-06-2000","published":false},{"id":27043,"page":[],"created":"10-09-1997","published":false},{"id":27044,"page":[],"created":"04-07-1995","published":false},{"id":27045,"page":[],"created":"16-06-1996","published":false},{"id":27046,"page":[],"created":"24-01-1997","published":false},{"id":27047,"page":[],"created":"30-05-1996","published":false},{"id":27048,"page":[],"created":"13-09-1996","published":false},{"id":27049,"page":[],"created":"15-09-1999","published":["18-02-2009"]},{"id":27050,"page":[],"created":"29-05-1996","published":false},{"id":27051,"page":[],"created":"30-05-1996","published":false},{"id":27052,"page":[],"created":"30-01-1997","published":false},{"id":27053,"page":[],"created":"01-01-1995","published":false},{"id":27054,"page":[],"created":"05-02-1997","published":false},{"id":27055,"page":[],"created":"01-01-1995","published":false},{"id":27056,"page":[],"created":"28-08-1996","published":false},{"id":27057,"page":[],"created":"21-07-1996","published":false},{"id":27058,"page":[],"created":"20-11-1996","published":false},{"id":27059,"page":[],"created":"09-12-1996","published":false},{"id":27060,"page":[],"created":"05-02-1997","published":false},{"id":27061,"page":[],"created":"23-05-1996","published":false},{"id":27062,"page":[],"created":"24-06-1997","published":false},{"id":27063,"page":[],"created":"01-01-1995","published":false},{"id":27064,"page":[],"created":"16-12-1996","published":false},{"id":27065,"page":[],"created":"31-05-1996","published":false},{"id":27066,"page":[],"created":"09-08-2001","published":false},{"id":27067,"page":[],"created":"01-01-1995","published":false},{"id":27068,"page":[],"created":"22-05-1996","published":false},{"id":27069,"page":[],"created":"11-06-1996","published":false},{"id":27070,"page":[],"created":"17-02-2000","published":false},{"id":27071,"page":[],"created":"04-11-1996","published":false},{"id":27072,"page":[],"created":"30-09-1998","published":false},{"id":27073,"page":[],"created":"12-04-2000","published":false},{"id":27074,"page":[],"created":"23-05-1996","published":false},{"id":27075,"page":[],"created":"23-04-1998","published":false},{"id":27076,"page":[],"created":"18-06-1996","published":false},{"id":27077,"page":[],"created":"14-11-1996","published":false},{"id":27078,"page":[],"created":"20-05-1996","published":false},{"id":27079,"page":[],"created":"01-01-1995","published":false},{"id":27080,"page":[],"created":"01-01-1995","published":false},{"id":27081,"page":[],"created":"25-06-1999","published":false},{"id":27082,"page":[],"created":"19-06-1996","published":false},{"id":27083,"page":[],"created":"01-01-1995","published":false},{"id":27084,"page":[],"created":"20-05-1996","published":false},{"id":27085,"page":[],"created":"23-05-1996","published":false},{"id":27086,"page":[],"created":"11-12-1996","published":false},{"id":27087,"page":[],"created":"21-05-1996","published":false},{"id":27088,"page":[],"created":"01-01-1995","published":false},{"id":27089,"page":[],"created":"21-01-1997","published":false},{"id":27090,"page":[],"created":"18-05-1999","published":false},{"id":27091,"page":[],"created":"20-06-1996","published":false},{"id":27092,"page":[],"created":"31-05-1996","published":false},{"id":27093,"page":[],"created":"24-05-1996","published":false},{"id":27094,"page":[{"id":669010517,"name":"1. Verantwoordelijke voor de verwerking","paragraph":[{"label":"Naam (of benaming rechtspersoon, feitelijke vereniging of openbaar bestuur)","value":"WAELKENS PAULA"},{"label":"Ondernemingsnummer\/BTW-nummer","value":"0"},{"label":"Straat","value":"BIESTSTRAAT"},{"label":"Huisnummer","value":"21"},{"label":"Postcode","value":"8790"},{"label":"Gemeente","value":"WAREGEM"},{"label":"Land","value":"BE"},{"label":"Juridisch statuut van de verantwoordelijke voor de verwerking","value":"4, 99, fysische persoon : ander vrij beroep"}]},{"id":337184732,"name":"1. Benaming van de verwerking","paragraph":[{"label":"1. Benaming van de verwerking","value":"PARAMEDA  RIZIV-ADMINISTRATIE"}]},false,false],"created":false,"published":false},{"id":27095,"page":[],"created":"01-01-1995","published":false},{"id":27096,"page":[],"created":"23-05-1996","published":false},{"id":27097,"page":[],"created":"01-01-1997","published":false},{"id":27098,"page":[],"created":"17-02-1998","published":false},{"id":27099,"page":[],"created":"15-01-2001","published":false},{"id":27100,"page":[],"created":"31-05-1996","published":false},{"id":27101,"page":[],"created":"01-01-1995","published":false},{"id":27102,"page":[],"created":"01-01-1995","published":false},{"id":27103,"page":[],"created":"20-03-1997","published":false},{"id":27104,"page":[],"created":"18-12-1996","published":false},{"id":27105,"page":[],"created":"12-03-2001","published":false},{"id":27106,"page":[],"created":"15-01-1997","published":false},{"id":27107,"page":[],"created":"01-01-1995","published":false},{"id":27108,"page":[],"created":"01-01-1995","published":false},{"id":27109,"page":[],"created":"22-05-1996","published":false},{"id":27110,"page":[],"created":"01-01-1995","published":false},{"id":27111,"page":[],"created":"30-05-1996","published":false},{"id":27112,"page":[],"created":"13-02-1998","published":false},{"id":27113,"page":[],"created":"01-01-1995","published":false},{"id":27114,"page":[],"created":"19-06-2001","published":false},{"id":27115,"page":[],"created":"01-01-1995","published":false},{"id":27116,"page":[],"created":"11-08-1998","published":false},{"id":27117,"page":[],"created":"01-01-1995","published":false},{"id":27118,"page":[],"created":"31-01-1997","published":false},{"id":27119,"page":[],"created":"06-06-2003","published":false},{"id":27120,"page":[],"created":"01-01-1995","published":false},{"id":27121,"page":[],"created":"26-05-1997","published":false},{"id":27122,"page":[],"created":"18-07-1997","published":false},{"id":27123,"page":[],"created":"10-06-1996","published":false},{"id":27124,"page":[],"created":"15-06-1996","published":false},{"id":27125,"page":[],"created":"30-07-1997","published":false},{"id":27126,"page":[],"created":"01-01-1995","published":["17-12-2008","10-06-2010"]},{"id":27127,"page":[{"id":1192756258,"name":"1. Verantwoordelijke voor de verwerking","paragraph":[{"label":"Naam (of benaming rechtspersoon, feitelijke vereniging of openbaar bestuur)","value":"V.Z.W. ST. JOZEFSINSTITUUT AFDELING GEZONDHEIDSCENTRUM"},{"label":"Gangbare afkorting van de naam van de verantwoordelijke","value":"MST TORHOUT"},{"label":"Straat","value":"PAPEBRUGSTRAAT"},{"label":"Huisnummer","value":"8"},{"label":"Postcode","value":"8820"},{"label":"Gemeente","value":"TORHOUT"},{"label":"Land","value":"BE"},{"label":"Juridisch statuut van de verantwoordelijke voor de verwerking","value":"Rechtspersoon, 17, rechtspersoon zonder winstoogmerk"}]},{"id":593933233,"name":"1. Benaming van de verwerking","paragraph":[{"label":"1. Benaming van de verwerking","value":"MEDISCH SCHOOLTOEZICHT"}]},false,false],"created":false,"published":false},{"id":27128,"page":[],"created":"01-01-1995","published":false},{"id":27129,"page":[],"created":"15-07-1997","published":false},{"id":27130,"page":[],"created":"16-11-1999","published":false},{"id":27131,"page":[],"created":"13-03-2001","published":false},{"id":27132,"page":[],"created":"21-10-1996","published":false},{"id":27133,"page":[],"created":"15-07-1996","published":false},{"id":27134,"page":[],"created":"20-12-1996","published":false},{"id":27135,"page":[],"created":"15-01-2001","published":false},{"id":27136,"page":[],"created":"12-05-2005","published":false},{"id":27137,"page":[],"created":"30-05-1996","published":false},{"id":27138,"page":[],"created":"25-09-2000","published":false},{"id":27139,"page":[],"created":"01-01-1995","published":false},{"id":27140,"page":[{"id":1875175363,"name":"1. Verantwoordelijke voor de verwerking","paragraph":[{"label":"Naam (of benaming rechtspersoon, feitelijke vereniging of openbaar bestuur)","value":"DESSEIN RAF"},{"label":"Ondernemingsnummer\/BTW-nummer","value":"BTW BE 0592.835.888"},{"label":"Straat","value":"STATIONSSTRAAT"},{"label":"Huisnummer","value":"33"},{"label":"Postcode","value":"9600"},{"label":"Gemeente","value":"RONSE"},{"label":"Land","value":"BE"},{"label":"Juridisch statuut van de verantwoordelijke voor de verwerking","value":", "}]},{"id":146609678,"name":"1. Benaming van de verwerking","paragraph":[{"label":"1. Benaming van de verwerking","value":"Afleveringsverwerking"}]},false,false],"created":false,"published":false},{"id":27141,"page":[],"created":"27-03-1997","published":false},{"id":27142,"page":[],"created":"29-11-1996","published":false},{"id":27143,"page":[],"created":"20-03-1997","published":false},{"id":27144,"page":[],"created":"06-07-2000","published":["09-09-2009"]},{"id":27145,"page":[],"created":"01-01-1995","published":false},{"id":27146,"page":[],"created":"10-02-1999","published":false},{"id":27147,"page":[],"created":"02-07-1996","published":false},{"id":27148,"page":[],"created":"29-05-1996","published":false},{"id":27149,"page":[],"created":"01-01-1995","published":false},{"id":27150,"page":[],"created":"23-05-1996","published":false},{"id":27151,"page":[],"created":"10-05-1996","published":false},{"id":27152,"page":[],"created":"12-11-1996","published":false},{"id":27153,"page":[],"created":"27-11-1995","published":false},{"id":27154,"page":[],"created":"29-08-1996","published":false},{"id":27155,"page":[],"created":"18-09-2002","published":false},{"id":27156,"page":[],"created":"28-05-1996","published":false},{"id":27157,"page":[],"created":"14-07-1997","published":false},{"id":27158,"page":[],"created":"03-07-1998","published":false},{"id":27159,"page":[],"created":"01-01-1995","published":false},{"id":27160,"page":[],"created":"01-01-1995","published":false},{"id":27161,"page":[],"created":"02-04-1997","published":false},{"id":27162,"page":[],"created":"01-01-1995","published":false},{"id":27163,"page":[],"created":"04-07-2001","published":false},{"id":27164,"page":[],"created":"31-07-2000","published":false},{"id":27165,"page":[],"created":"01-01-1995","published":false},{"id":27166,"page":[],"created":"01-01-1995","published":false},{"id":27167,"page":[],"created":"22-08-1996","published":false},{"id":27168,"page":[],"created":"01-01-1995","published":false},{"id":27169,"page":[],"created":"29-05-1996","published":false},{"id":27170,"page":[],"created":"20-08-1996","published":false},{"id":27171,"page":[],"created":"31-07-1996","published":false},{"id":27172,"page":[],"created":"01-04-1999","published":false},{"id":27173,"page":[],"created":"13-02-1997","published":false},{"id":27174,"page":[],"created":"10-02-1997","published":false},{"id":27175,"page":[],"created":"23-02-1999","published":false},{"id":27176,"page":[],"created":"29-01-2001","published":false},{"id":27177,"page":[],"created":"01-01-1995","published":false},{"id":27178,"page":[],"created":"11-06-1995","published":false},{"id":27179,"page":[],"created":"01-01-1995","published":false},{"id":27180,"page":[],"created":"01-07-1996","published":false},{"id":27181,"page":[],"created":"23-04-1997","published":false},{"id":27182,"page":[],"created":"01-06-1996","published":false},{"id":27183,"page":[],"created":"01-01-1995","published":false},{"id":27184,"page":[],"created":"29-05-1996","published":false},{"id":27185,"page":[],"created":"01-01-1995","published":false},{"id":27186,"page":[],"created":"31-07-1996","published":false},{"id":27187,"page":[],"created":"31-05-1996","published":false},{"id":27188,"page":[],"created":"30-10-1996","published":false},{"id":27189,"page":[],"created":"31-07-2000","published":false},{"id":27190,"page":[],"created":"01-01-1995","published":false},{"id":27191,"page":[],"created":"30-05-1996","published":["06-03-2008","30-04-2010"]},{"id":27192,"page":[],"created":"25-11-1996","published":false},{"id":27193,"page":[],"created":"01-01-1995","published":false},{"id":27194,"page":[],"created":"21-08-1996","published":["29-04-2008"]},{"id":27195,"page":[],"created":"01-12-1999","published":false},{"id":27196,"page":[],"created":"14-11-1996","published":false},{"id":27197,"page":[],"created":"19-08-1996","published":false},{"id":27198,"page":[],"created":"28-05-1996","published":false},{"id":27199,"page":[],"created":"10-02-1997","published":false},{"id":27200,"page":[],"created":"01-01-1995","published":false},{"id":27201,"page":[],"created":"12-05-1996","published":false},{"id":27202,"page":[],"created":"29-03-1995","published":false},{"id":27203,"page":[],"created":"13-08-1995","published":false},{"id":27204,"page":[],"created":"14-10-1998","published":false},{"id":27205,"page":[],"created":"01-01-1995","published":false},{"id":27206,"page":[],"created":"20-05-1997","published":false},{"id":27207,"page":[],"created":"01-01-1995","published":false},{"id":27208,"page":[],"created":"01-01-1995","published":false},{"id":27209,"page":[],"created":"01-01-1995","published":false},{"id":27210,"page":[],"created":"01-01-1995","published":false},{"id":27211,"page":[],"created":"12-05-1997","published":false},{"id":27212,"page":[],"created":"01-01-1995","published":false},{"id":27213,"page":[],"created":"01-01-1995","published":false},{"id":27214,"page":[],"created":"13-03-2000","published":false},{"id":27215,"page":[],"created":"16-06-1996","published":false},{"id":27216,"page":[],"created":"07-06-1996","published":false},{"id":27217,"page":[],"created":"31-07-1996","published":false},{"id":27218,"page":[],"created":"01-01-1995","published":false},{"id":27219,"page":[],"created":"09-05-1996","published":false},{"id":27220,"page":[],"created":"29-05-1996","published":false},{"id":27221,"page":[],"created":"01-08-1996","published":false},{"id":27222,"page":[],"created":"14-06-1996","published":false},{"id":27223,"page":[],"created":"26-08-1996","published":false},{"id":27224,"page":[],"created":"01-01-1995","published":false},{"id":27225,"page":[],"created":"18-02-2000","published":["08-04-2008","07-05-2010"]},{"id":27226,"page":[],"created":"28-04-1996","published":false},{"id":27227,"page":[],"created":"24-11-2005","published":["08-12-2009","01-03-2011","18-10-2011","06-07-2012"]},{"id":27228,"page":[],"created":"29-01-1997","published":false},{"id":27229,"page":[],"created":"04-08-1995","published":false},{"id":27230,"page":[],"created":"01-01-1995","published":false},{"id":27231,"page":[],"created":"01-09-2006","published":false},{"id":27232,"page":[],"created":"01-01-1995","published":false},{"id":27233,"page":[],"created":"08-10-2001","published":false},{"id":27234,"page":[],"created":"28-08-1995","published":false},{"id":27235,"page":[],"created":"01-01-1995","published":false},{"id":27236,"page":[],"created":"23-09-2004","published":false},{"id":27237,"page":[],"created":"18-06-1996","published":false},{"id":27238,"page":[],"created":"14-09-1995","published":false},{"id":27239,"page":[],"created":"01-01-1995","published":["19-03-2012","13-08-2012"]},{"id":27240,"page":[],"created":"29-01-2001","published":false},{"id":27241,"page":[],"created":"14-08-1998","published":false},{"id":27242,"page":[],"created":"02-02-2001","published":false},{"id":27243,"page":[],"created":"21-05-1997","published":false},{"id":27244,"page":[],"created":"24-02-1997","published":false},{"id":27245,"page":[],"created":"28-07-1997","published":false},{"id":27246,"page":[],"created":"23-11-2000","published":false},{"id":27247,"page":[],"created":"15-10-1999","published":false},{"id":27248,"page":[],"created":"23-12-1996","published":false},{"id":27249,"page":[],"created":"31-08-1996","published":false},{"id":27250,"page":[],"created":"31-05-1996","published":false},{"id":27251,"page":[],"created":"30-05-1997","published":false},{"id":27252,"page":[],"created":"01-01-1995","published":false},{"id":27253,"page":[],"created":"02-04-1997","published":false},{"id":27254,"page":[],"created":"28-07-1999","published":false},{"id":27255,"page":[],"created":"31-05-1996","published":false},{"id":27256,"page":[],"created":"29-06-1998","published":false},{"id":27257,"page":[],"created":"25-02-2000","published":false},{"id":27258,"page":[],"created":"21-09-2000","published":false},{"id":27259,"page":[],"created":"01-06-1995","published":false},{"id":27260,"page":[],"created":"15-01-2001","published":false},{"id":27261,"page":[],"created":"04-11-1996","published":false},{"id":27262,"page":[],"created":"06-01-1997","published":false},{"id":27263,"page":[],"created":"05-05-1999","published":false},{"id":27264,"page":[],"created":"23-07-1997","published":false},{"id":27265,"page":[],"created":"01-01-1995","published":false},{"id":27266,"page":[],"created":"01-01-1995","published":false},{"id":27267,"page":[],"created":"01-01-1995","published":false},{"id":27268,"page":[],"created":"25-07-1996","published":false},{"id":27269,"page":[],"created":"13-06-1996","published":false},{"id":27270,"page":[],"created":"02-04-1997","published":false},{"id":27271,"page":[],"created":"10-06-1996","published":false},{"id":27272,"page":[],"created":"12-01-1998","published":false},{"id":27273,"page":[],"created":"12-07-2000","published":false},{"id":27274,"page":[],"created":"31-05-1996","published":false},{"id":27275,"page":[],"created":"31-05-1996","published":false},{"id":27276,"page":[],"created":"10-10-2001","published":false},{"id":27277,"page":[],"created":"04-12-1996","published":false},{"id":27278,"page":[],"created":"15-06-1997","published":false},{"id":27279,"page":[],"created":"19-03-1999","published":["11-05-2009","28-11-2011","08-02-2012"]},{"id":27280,"page":[],"created":"21-06-2001","published":false},{"id":27281,"page":[],"created":"19-03-1997","published":false},{"id":27282,"page":[],"created":"14-05-1997","published":false},{"id":27283,"page":[],"created":"01-06-1997","published":false},{"id":27284,"page":[],"created":"01-01-1995","published":false},{"id":27285,"page":[],"created":"05-09-1996","published":false},{"id":27286,"page":[],"created":"31-05-1996","published":false},{"id":27287,"page":[],"created":"01-01-1995","published":false},{"id":27288,"page":[],"created":"15-05-1997","published":false},{"id":27289,"page":[],"created":"16-03-2001","published":false},{"id":27290,"page":[],"created":"27-08-1996","published":false},{"id":27291,"page":[],"created":"11-12-2001","published":false},{"id":27292,"page":[],"created":"13-11-1996","published":false},{"id":27293,"page":[{"id":597515327,"name":"1. Verantwoordelijke voor de verwerking","paragraph":[{"label":"Naam (of benaming rechtspersoon, feitelijke vereniging of openbaar bestuur)","value":"Dexia Banque Belgique (anciennement Cr\u00e9dit Communal de Belgique)"},{"label":"Eventuele vertaling van de naam of andere benaming","value":"Dexia Bank Belgi\u00eb"},{"label":"Gangbare afkorting van de naam van de verantwoordelijke","value":"Dexia Banque"},{"label":"Eventuele vertaling van de gangbare afkorting","value":"Dexia Bank"},{"label":"Ondernemingsnummer\/BTW-nummer","value":"BTW BE 0458.522.859"},{"label":"Straat","value":"boulevard Pach\u00e9co"},{"label":"Huisnummer","value":"44"},{"label":"Postcode","value":"1000"},{"label":"Gemeente","value":"BRUXELLES"},{"label":"Land","value":"BE"},{"label":"Juridisch statuut van de verantwoordelijke voor de verwerking","value":"4, 99, personne morale : soci\u00e9t\u00e9 commerciale"}]},{"id":1413214788,"name":"1. Benaming van de verwerking","paragraph":[{"label":"1. Benaming van de verwerking","value":"CONTROLE DES OPERATIONS"}]},false,false],"created":false,"published":false},{"id":27294,"page":[],"created":"03-07-2001","published":false},{"id":27295,"page":[],"created":"11-12-1996","published":false},{"id":27296,"page":[],"created":"01-01-1995","published":false},{"id":27297,"page":[],"created":"15-05-1996","published":false},{"id":27298,"page":[],"created":"03-02-1997","published":false},{"id":27299,"page":[],"created":"19-10-1995","published":false},{"id":27300,"page":[],"created":"13-03-2000","published":false},{"id":27301,"page":[],"created":"23-05-1997","published":false},{"id":27302,"page":[],"created":"28-05-1996","published":false},{"id":27303,"page":[],"created":"30-05-1996","published":false},{"id":27304,"page":[],"created":"20-08-1996","published":false},{"id":27305,"page":[],"created":"29-12-2000","published":["02-09-2013"]},{"id":27306,"page":[],"created":"02-05-1997","published":false},{"id":27307,"page":[],"created":"19-12-1997","published":false},{"id":27308,"page":[],"created":"24-11-1995","published":false},{"id":27309,"page":[],"created":"03-05-1997","published":false},{"id":27310,"page":[],"created":"05-04-1997","published":false},{"id":27311,"page":[],"created":"01-08-1996","published":false},{"id":27312,"page":[],"created":"10-10-1995","published":false},{"id":27313,"page":[],"created":"01-01-1995","published":false},{"id":27314,"page":[],"created":"01-01-1995","published":false},{"id":27315,"page":[],"created":"05-06-1996","published":false},{"id":27316,"page":[],"created":"20-02-1997","published":false},{"id":27317,"page":[],"created":"16-05-1997","published":false},{"id":27318,"page":[],"created":"01-01-1995","published":false},{"id":27319,"page":[],"created":"12-07-1996","published":false},{"id":27320,"page":[],"created":"01-01-1995","published":false},{"id":27321,"page":[],"created":"25-06-1996","published":false},{"id":27322,"page":[],"created":"23-09-1997","published":false},{"id":27323,"page":[],"created":"30-08-1996","published":false},{"id":27324,"page":[{"id":449702990,"name":"1. Verantwoordelijke voor de verwerking","paragraph":[{"label":"Naam (of benaming rechtspersoon, feitelijke vereniging of openbaar bestuur)","value":"Kliniek Zwarte Zusters"},{"label":"Eventuele vertaling van de naam of andere benaming","value":"Clinique des Soeurs Noires"},{"label":"Gangbare afkorting van de naam van de verantwoordelijke","value":"KZZ"},{"label":"Straat","value":"Rijselsestraat"},{"label":"Huisnummer","value":"85"},{"label":"Postcode","value":"8900"},{"label":"Gemeente","value":"IEPER"},{"label":"Land","value":"BE"},{"label":"Juridisch statuut van de verantwoordelijke voor de verwerking","value":"4, 99, feitelijke vereniging zonder winstoogmerk"}]},{"id":1339865508,"name":"1. Benaming van de verwerking","paragraph":[{"label":"1. Benaming van de verwerking","value":"MVG - MKG"}]},false,false],"created":false,"published":false},{"id":27325,"page":[],"created":"07-11-1995","published":false},{"id":27326,"page":[],"created":"09-12-1997","published":false},{"id":27327,"page":[],"created":"05-09-2000","published":false},{"id":27328,"page":[],"created":"27-11-1997","published":false},{"id":27329,"page":[],"created":"01-01-1995","published":false},{"id":27330,"page":[],"created":"01-01-1995","published":false},{"id":27331,"page":[],"created":"01-01-1995","published":false},{"id":27332,"page":[],"created":"24-05-1996","published":false},{"id":27333,"page":[],"created":"20-02-1997","published":false},{"id":27334,"page":[],"created":"20-01-1998","published":false},{"id":27335,"page":[],"created":"25-09-1998","published":false},{"id":27336,"page":[],"created":"30-01-2003","published":false},{"id":27337,"page":[],"created":"01-01-1995","published":false},{"id":27338,"page":[],"created":"01-01-1995","published":false},{"id":27339,"page":[],"created":"12-12-1996","published":false},{"id":27340,"page":[],"created":"01-01-1995","published":false},{"id":27341,"page":[],"created":"01-01-1995","published":false},{"id":27342,"page":[],"created":"22-05-1996","published":false},{"id":27343,"page":[],"created":"12-05-1997","published":false},{"id":27344,"page":[],"created":"04-11-1998","published":false},{"id":27345,"page":[],"created":"01-01-1995","published":false},{"id":27346,"page":[],"created":"01-01-1995","published":false},{"id":27347,"page":[],"created":"07-06-1996","published":false},{"id":27348,"page":[],"created":"20-07-1997","published":false},{"id":27349,"page":[],"created":"01-01-1995","published":false},{"id":27350,"page":[],"created":"01-01-1995","published":false},{"id":27351,"page":[],"created":"01-01-1995","published":false},{"id":27352,"page":[],"created":"31-01-2005","published":false},{"id":27353,"page":[],"created":"22-05-1996","published":false},{"id":27354,"page":[],"created":"04-09-1997","published":false},{"id":27355,"page":[],"created":"14-11-1996","published":false},{"id":27356,"page":[],"created":"04-06-1996","published":false},{"id":27357,"page":[],"created":"17-12-1996","published":false},{"id":27358,"page":[],"created":"01-12-1999","published":false},{"id":27359,"page":[],"created":"09-07-1996","published":false},{"id":27360,"page":[],"created":"05-02-1997","published":false},{"id":27361,"page":[],"created":"01-01-1995","published":false},{"id":27362,"page":[],"created":"29-05-1996","published":false},{"id":27363,"page":[],"created":"30-05-1996","published":false},{"id":27364,"page":[],"created":"01-01-1995","published":false},{"id":27365,"page":[],"created":"20-08-1996","published":false},{"id":27366,"page":[],"created":"18-02-1999","published":false},{"id":27367,"page":[],"created":"10-03-1997","published":false},{"id":27368,"page":[],"created":"01-01-1995","published":false},{"id":27369,"page":[],"created":"01-01-1995","published":false},{"id":27370,"page":[],"created":"25-07-1995","published":false},{"id":27371,"page":[],"created":"06-09-2000","published":false},{"id":27372,"page":[],"created":"17-02-1997","published":false},{"id":27373,"page":[],"created":"01-07-1996","published":false},{"id":27374,"page":[],"created":"25-04-1997","published":false},{"id":27375,"page":[],"created":"25-03-1997","published":false},{"id":27376,"page":[],"created":"31-05-1996","published":false},{"id":27377,"page":[],"created":"22-04-1997","published":false},{"id":27378,"page":[],"created":"19-09-1996","published":false},{"id":27379,"page":[],"created":"01-01-1995","published":false},{"id":27380,"page":[],"created":"21-02-2001","published":false},{"id":27381,"page":[],"created":"28-05-1996","published":false},{"id":27382,"page":[],"created":"01-01-1995","published":false},{"id":27383,"page":[],"created":"26-05-1997","published":false},{"id":27384,"page":[],"created":"23-04-1997","published":false},{"id":27385,"page":[],"created":"31-05-1996","published":false},{"id":27386,"page":[],"created":"01-01-1995","published":false},{"id":27387,"page":[],"created":"10-07-1997","published":false},{"id":27388,"page":[],"created":"15-04-1998","published":false},{"id":27389,"page":[],"created":"03-02-1997","published":false},{"id":27390,"page":[],"created":"01-01-1995","published":false},{"id":27391,"page":[],"created":"01-01-1995","published":false},{"id":27392,"page":[],"created":"29-08-1996","published":false},{"id":27393,"page":[],"created":"06-08-1997","published":["11-05-2011"]},{"id":27394,"page":[],"created":"14-07-1997","published":false},{"id":27395,"page":[],"created":"26-10-1995","published":false},{"id":27396,"page":[],"created":"24-05-1996","published":false},{"id":27397,"page":[],"created":"30-09-1996","published":false},{"id":27398,"page":[],"created":"01-01-1995","published":false},{"id":27399,"page":[],"created":"25-06-1996","published":false},{"id":27400,"page":[],"created":"01-01-1995","published":false},{"id":27401,"page":[],"created":"28-05-1996","published":false},{"id":27402,"page":[],"created":"01-01-1995","published":false},{"id":27403,"page":[],"created":"07-06-1996","published":false},{"id":27404,"page":[],"created":"22-11-2000","published":false},{"id":27405,"page":[],"created":"25-10-1996","published":false},{"id":27406,"page":[],"created":"09-07-1996","published":false},{"id":27407,"page":[],"created":"01-01-1995","published":false},{"id":27408,"page":[],"created":"08-04-1997","published":false},{"id":27409,"page":[],"created":"07-11-1997","published":false},{"id":27410,"page":[],"created":"14-07-2000","published":false},{"id":27411,"page":[],"created":"20-09-1999","published":false},{"id":27412,"page":[],"created":"14-12-1999","published":false},{"id":27413,"page":[],"created":"01-01-1996","published":false},{"id":27414,"page":[],"created":"02-10-1995","published":false},{"id":27415,"page":[],"created":"15-04-1997","published":false},{"id":27416,"page":[],"created":"01-01-1995","published":false},{"id":27417,"page":[],"created":"01-01-1995","published":false},{"id":27418,"page":[],"created":"31-05-1996","published":false},{"id":27419,"page":[],"created":"17-04-1998","published":false},{"id":27420,"page":[],"created":"01-01-1995","published":false},{"id":27421,"page":[],"created":"01-04-1997","published":false},{"id":27422,"page":[],"created":"20-11-1996","published":false},{"id":27423,"page":[],"created":"23-08-1996","published":false},{"id":27424,"page":[],"created":"01-01-1995","published":false},{"id":27425,"page":[],"created":"02-08-2000","published":false},{"id":27426,"page":[],"created":"01-01-1996","published":false},{"id":27427,"page":[],"created":"02-12-1997","published":false},{"id":27428,"page":[],"created":"27-05-1997","published":false},{"id":27429,"page":[],"created":"24-05-1996","published":false},{"id":27430,"page":[],"created":"25-09-1995","published":false},{"id":27431,"page":[],"created":"27-08-1996","published":false},{"id":27432,"page":[],"created":"07-10-2002","published":["30-07-2009","27-11-2012"]},{"id":27433,"page":[],"created":"01-01-1995","published":false},{"id":27434,"page":[],"created":"28-04-1997","published":false},{"id":27435,"page":[],"created":"20-01-1997","published":false},{"id":27436,"page":[],"created":"01-01-1995","published":false},{"id":27437,"page":[],"created":"29-12-1996","published":false},{"id":27438,"page":[],"created":"13-06-1995","published":false},{"id":27439,"page":[],"created":"21-05-1996","published":false},{"id":27440,"page":[],"created":"08-10-1998","published":false},{"id":27441,"page":[],"created":"23-05-1997","published":false},{"id":27442,"page":[],"created":"30-06-1996","published":false},{"id":27443,"page":[],"created":"01-01-1995","published":false},{"id":27444,"page":[],"created":"17-01-1997","published":false},{"id":27445,"page":[],"created":"10-02-1997","published":false},{"id":27446,"page":[],"created":"19-12-1996","published":false},{"id":27447,"page":[],"created":"04-09-1996","published":false},{"id":27448,"page":[],"created":"11-12-1996","published":false},{"id":27449,"page":[],"created":"21-09-1996","published":false},{"id":27450,"page":[],"created":"05-08-1996","published":false},{"id":27451,"page":[],"created":"06-01-1997","published":false},{"id":27452,"page":[],"created":"22-07-1996","published":false},{"id":27453,"page":[],"created":"17-06-1996","published":false},{"id":27454,"page":[],"created":"02-07-1998","published":false},{"id":27455,"page":[],"created":"01-01-1995","published":false},{"id":27456,"page":[],"created":"01-01-1995","published":false},{"id":27457,"page":[],"created":"24-06-1996","published":false},{"id":27458,"page":[],"created":"29-05-1996","published":false},{"id":27459,"page":[],"created":"01-01-1995","published":false},{"id":27460,"page":[],"created":"28-05-1996","published":false},{"id":27461,"page":[],"created":"15-01-1997","published":false},{"id":27462,"page":[],"created":"10-10-2001","published":false},{"id":27463,"page":[],"created":"01-01-1995","published":false},{"id":27464,"page":[],"created":"15-05-1997","published":false},{"id":27465,"page":[],"created":"25-10-1998","published":false},{"id":27466,"page":[],"created":"18-06-1996","published":false},{"id":27467,"page":[],"created":"22-04-1997","published":false},{"id":27468,"page":[],"created":"30-07-1998","published":false},{"id":27469,"page":[],"created":"01-10-1998","published":false},{"id":27470,"page":[],"created":"14-05-1997","published":false},{"id":27471,"page":[],"created":"30-08-2000","published":false},{"id":27472,"page":[],"created":"27-08-1996","published":false},{"id":27473,"page":[],"created":"11-01-2001","published":false},{"id":27474,"page":[],"created":"12-07-1996","published":false},{"id":27475,"page":[],"created":"27-08-1996","published":false},{"id":27476,"page":[],"created":"30-05-1996","published":false},{"id":27477,"page":[],"created":"25-07-1996","published":false},{"id":27478,"page":[],"created":"19-01-1999","published":false},{"id":27479,"page":[],"created":"31-05-1996","published":false},{"id":27480,"page":[],"created":"29-05-1997","published":false},{"id":27481,"page":[],"created":"29-04-1997","published":false},{"id":27482,"page":[],"created":"19-01-2000","published":false},{"id":27483,"page":[],"created":"25-05-1996","published":false},{"id":27484,"page":[],"created":"17-12-1996","published":false},{"id":27485,"page":[],"created":"01-01-1995","published":false},{"id":27486,"page":[],"created":"24-07-1996","published":false},{"id":27487,"page":[],"created":"17-04-1999","published":false},{"id":27488,"page":[],"created":"11-02-1997","published":false},{"id":27489,"page":[],"created":"17-05-1997","published":false},{"id":27490,"page":[],"created":"22-11-1996","published":false},{"id":27491,"page":[],"created":"04-02-1997","published":false},{"id":27492,"page":[],"created":"20-01-1997","published":false},{"id":27493,"page":[],"created":"12-09-1996","published":false},{"id":27494,"page":[],"created":"31-05-1996","published":false},{"id":27495,"page":[],"created":"23-07-1998","published":false},{"id":27496,"page":[],"created":"22-05-1996","published":false},{"id":27497,"page":[],"created":"01-01-1995","published":false},{"id":27498,"page":[],"created":"17-06-1996","published":false},{"id":27499,"page":[],"created":"01-01-1995","published":false}]